{
  "gate": "L3-12-long-video",
  "profile": "full",
  "pass": true,
  "checks": [
    {
      "id": "gate-wrapper-process",
      "pass": true,
      "measured": {
        "command": "/usr/bin/node src/gates/p5-l3-12-long-video.mjs --profile full --json",
        "exitCode": 0,
        "signal": null,
        "error": null,
        "profile": "full",
        "parseError": null,
        "stderrTail": "",
        "stdoutTail": ""
      }
    },
    {
      "id": "profile-full-required",
      "pass": true,
      "measured": {
        "profile": "full",
        "reason": "L3-12 runs the actual long render and is full-profile only"
      }
    },
    {
      "id": "gate-parameters",
      "pass": true,
      "measured": {
        "sceneCount": 12,
        "minDurationSec": 120,
        "reduction": "P5-pre-resume timeout recovery uses 12 scenes and a 2min minimum instead of the prior 20 scenes and 3min minimum",
        "verdictCriteria": "complete render, peak RSS recorded, no OOM/SIGKILL signature"
      }
    },
    {
      "id": "generated-scene-specs-12-scenes",
      "pass": true,
      "measured": {
        "project": "tmp/gate-work/p5/l3-12-long-video/project",
        "sceneSpecs": "tmp/gate-work/p5/l3-12-long-video/project/scene_specs.json",
        "scenes": 12,
        "transitions": 11,
        "gateParameters": {
          "sceneCount": 12,
          "minDurationSec": 120,
          "reduction": "P5-pre-resume timeout recovery uses 12 scenes and a 2min minimum instead of the prior 20 scenes and 3min minimum",
          "verdictCriteria": "complete render, peak RSS recorded, no OOM/SIGKILL signature"
        }
      }
    },
    {
      "id": "mock-pipeline-through-compile",
      "pass": true,
      "measured": {
        "command": "/usr/bin/node bin/vf pipeline run tmp/gate-work/p5/l3-12-long-video/project --profile mock --force --until compile",
        "exitCode": 0,
        "signal": null,
        "stdoutSummary": [
          "pipeline: START project=tmp/gate-work/p5/l3-12-long-video/project profile=mock steps=tts,images,compile",
          "pipeline: RUN tts reason=force inputHash=ce498831deb8",
          "pipeline: DONE tts provider=mock-tts scenes=12",
          "pipeline: RUN images reason=force inputHash=d9156d567f31",
          "pipeline: DONE images provider=mock-image scenes=0 generated=0 reused=0 manifest=image-manifest.json",
          "pipeline: RUN compile reason=force inputHash=176ed933f193",
          "pipeline: DONE compile",
          "pipeline: PASS completed=tts,images,compile"
        ],
        "stderrTail": ""
      }
    },
    {
      "id": "long-render-completes",
      "pass": true,
      "measured": {
        "command": "/usr/bin/time -v /usr/bin/env NODE_OPTIONS=--max-old-space-size=6144 /home/seunghyeong/reelforge/node_modules/.bin/hyperframes render /home/seunghyeong/reelforge/tmp/gate-work/p5/l3-12-long-video/project/build --output /home/seunghyeong/reelforge/tmp/gate-work/p5/l3-12-long-video/project/out/main.mp4 --fps=30 --quality=standard --workers=1 --no-browser-gpu --browser-timeout=360 --player-ready-timeout=360000 --protocol-timeout=600000",
        "exitCode": 0,
        "signal": null,
        "output": "tmp/gate-work/p5/l3-12-long-video/project/out/main.mp4",
        "bytes": 7547701,
        "stdoutTail": "█████████░░░░░  80%  Streaming frame 4313/4344\r\u001b[2K  ████████████████████░░░░░  80%  Streaming frame 4314/4344\r\u001b[2K  ████████████████████░░░░░  80%  Streaming frame 4315/4344\r\u001b[2K  ████████████████████░░░░░  80%  Streaming frame 4316/4344\r\u001b[2K  ████████████████████░░░░░  80%  Streaming frame 4317/4344\r\u001b[2K  ████████████████████░░░░░  80%  Streaming frame 4318/4344\r\u001b[2K  ████████████████████░░░░░  80%  Streaming frame 4319/4344\r\u001b[2K  ████████████████████░░░░░  80%  Streaming frame 4320/4344\r\u001b[2K  ████████████████████░░░░░  80%  Streaming frame 4321/4344\r\u001b[2K  ████████████████████░░░░░  80%  Streaming frame 4322/4344\r\u001b[2K  ████████████████████░░░░░  80%  Streaming frame 4323/4344\r\u001b[2K  ████████████████████░░░░░  80%  Streaming frame 4324/4344\r\u001b[2K  ████████████████████░░░░░  80%  Streaming frame 4325/4344\r\u001b[2K  ████████████████████░░░░░  80%  Streaming frame 4326/4344\r\u001b[2K  ████████████████████░░░░░  80%  Streaming frame 4327/4344\r\u001b[2K  ████████████████████░░░░░  80%  Streaming frame 4328/4344\r\u001b[2K  ████████████████████░░░░░  80%  Streaming frame 4329/4344\r\u001b[2K  ████████████████████░░░░░  80%  Streaming frame 4330/4344\r\u001b[2K  ████████████████████░░░░░  80%  Streaming frame 4331/4344\r\u001b[2K  ████████████████████░░░░░  80%  Streaming frame 4332/4344\r\u001b[2K  ████████████████████░░░░░  80%  Streaming frame 4333/4344\r\u001b[2K  ████████████████████░░░░░  80%  Streaming frame 4334/4344\r\u001b[2K  ████████████████████░░░░░  80%  Streaming frame 4335/4344\r\u001b[2K  ████████████████████░░░░░  80%  Streaming frame 4336/4344\r\u001b[2K  ████████████████████░░░░░  80%  Streaming frame 4337/4344\r\u001b[2K  ████████████████████░░░░░  80%  Streaming frame 4338/4344\r\u001b[2K  ████████████████████░░░░░  80%  Streaming frame 4339/4344\r\u001b[2K  ████████████████████░░░░░  80%  Streaming frame 4340/4344\r\u001b[2K  ████████████████████░░░░░  80%  Streaming frame 4341/4344\r\u001b[2K  ████████████████████░░░░░  80%  Streaming frame 4342/4344\r\u001b[2K  ████████████████████░░░░░  80%  Streaming frame 4343/4344\r\u001b[2K  ████████████████████░░░░░  80%  Streaming frame 4344/4344[static-dedup] reused 3984/4344 frame(s) (92%), est. ~354576ms saved (avg 89ms/frame)\n[INFO] [Render:trace] {\"renderJobId\":\"dcbc3cb6-14fe-4ee4-a5c7-f93a0e648d9e\",\"phase\":\"capture_streaming\",\"status\":\"end\",\"elapsedMs\":78856,\"durationMs\":71345}\n[INFO] [Render:trace] {\"renderJobId\":\"dcbc3cb6-14fe-4ee4-a5c7-f93a0e648d9e\",\"phase\":\"assemble\",\"status\":\"start\",\"elapsedMs\":78856,\"hasAudio\":true}\n\r\u001b[2K  ██████████████████████░░░  90%  Assembling final video[INFO] [Render:trace] {\"renderJobId\":\"dcbc3cb6-14fe-4ee4-a5c7-f93a0e648d9e\",\"phase\":\"assemble\",\"status\":\"end\",\"elapsedMs\":79149,\"durationMs\":293}\n\r\u001b[2K  █████████████████████████  100%  Render complete[INFO] [Render:trace] {\"renderJobId\":\"dcbc3cb6-14fe-4ee4-a5c7-f93a0e648d9e\",\"phase\":\"pipeline\",\"status\":\"checkpoint\",\"elapsedMs\":79150,\"message\":\"completed\",\"totalElapsedMs\":79149}\n\n◇  /home/seunghyeong/reelforge/tmp/gate-work/p5/l3-12-long-video/project/out/main.mp4\n   7.2 MB · 2m 24.8s video · rendered in 1m 19.2s\n",
        "stderrTail": "\tCommand being timed: \"/usr/bin/env NODE_OPTIONS=--max-old-space-size=6144 /home/seunghyeong/reelforge/node_modules/.bin/hyperframes render /home/seunghyeong/reelforge/tmp/gate-work/p5/l3-12-long-video/project/build --output /home/seunghyeong/reelforge/tmp/gate-work/p5/l3-12-long-video/project/out/main.mp4 --fps=30 --quality=standard --workers=1 --no-browser-gpu --browser-timeout=360 --player-ready-timeout=360000 --protocol-timeout=600000\"\n\tUser time (seconds): 168.87\n\tSystem time (seconds): 21.06\n\tPercent of CPU this job got: 238%\n\tElapsed (wall clock) time (h:mm:ss or m:ss): 1:19.78\n\tAverage shared text size (kbytes): 0\n\tAverage unshared data size (kbytes): 0\n\tAverage stack size (kbytes): 0\n\tAverage total size (kbytes): 0\n\tMaximum resident set size (kbytes): 2955200\n\tAverage resident set size (kbytes): 0\n\tMajor (requiring I/O) page faults: 4183\n\tMinor (reclaiming a frame) page faults: 6159562\n\tVoluntary context switches: 393213\n\tInvoluntary context switches: 28848\n\tSwaps: 0\n\tFile system inputs: 296\n\tFile system outputs: 523320\n\tSocket messages sent: 0\n\tSocket messages received: 0\n\tSignals delivered: 0\n\tPage size (bytes): 4096\n\tExit status: 0\n",
        "time": {
          "peakRssKb": 2955200,
          "elapsed": "1:19.78",
          "userSec": 168.87,
          "systemSec": 21.06
        }
      }
    },
    {
      "id": "peak-rss-recorded",
      "pass": true,
      "measured": {
        "method": "/usr/bin/time -v",
        "peakRssKb": 2955200,
        "peakRssMb": 2885.9,
        "elapsed": "1:19.78",
        "userSec": 168.87,
        "systemSec": 21.06
      }
    },
    {
      "id": "oom-signature-absent",
      "pass": true,
      "measured": {
        "setupExitCode": 0,
        "renderExitCode": 0,
        "setupSignal": null,
        "renderSignal": null,
        "peakRssKb": 2955200,
        "scanned": [
          "stdout",
          "stderr"
        ],
        "oomPattern": "out of memory|heap|ENOMEM|OOM|Killed"
      }
    },
    {
      "id": "pipeline-gate-completes",
      "pass": true,
      "measured": {
        "command": "/usr/bin/node bin/vf pipeline run tmp/gate-work/p5/l3-12-long-video/project --profile mock --only gate",
        "exitCode": 0,
        "signal": null,
        "stdoutSummary": [
          "pipeline: START project=tmp/gate-work/p5/l3-12-long-video/project profile=mock steps=gate",
          "pipeline: RUN gate reason=missing-outputs inputHash=39bbcdd61b5b",
          "pipeline: DONE gate report=reports/pipeline-gate-report.json",
          "pipeline: PASS completed=tts,images,compile,gate"
        ],
        "stderrTail": "",
        "report": "tmp/gate-work/p5/l3-12-long-video/project/reports/pipeline-gate-report.json",
        "reportPass": true,
        "reportExitCode": 0
      }
    },
    {
      "id": "mock-pipeline-completes",
      "pass": true,
      "measured": {
        "note": "P5 gate runs mock pipeline through compile, renders with an extended browser timeout, then runs the pipeline gate step against the render output.",
        "setupCommand": "/usr/bin/node bin/vf pipeline run tmp/gate-work/p5/l3-12-long-video/project --profile mock --force --until compile",
        "renderCommand": "/usr/bin/time -v /usr/bin/env NODE_OPTIONS=--max-old-space-size=6144 /home/seunghyeong/reelforge/node_modules/.bin/hyperframes render /home/seunghyeong/reelforge/tmp/gate-work/p5/l3-12-long-video/project/build --output /home/seunghyeong/reelforge/tmp/gate-work/p5/l3-12-long-video/project/out/main.mp4 --fps=30 --quality=standard --workers=1 --no-browser-gpu --browser-timeout=360 --player-ready-timeout=360000 --protocol-timeout=600000",
        "gateCommand": "/usr/bin/node bin/vf pipeline run tmp/gate-work/p5/l3-12-long-video/project --profile mock --only gate",
        "setupExitCode": 0,
        "renderExitCode": 0,
        "gateExitCode": 0
      }
    },
    {
      "id": "actual-render-duration-2min-plus",
      "pass": true,
      "measured": {
        "output": "tmp/gate-work/p5/l3-12-long-video/project/out/main.mp4",
        "bytes": 7547701,
        "minDurationSec": 120,
        "actualDurationSec": 144.832,
        "expectedDurationSec": 144.79999998800002,
        "ffprobe": {
          "command": "ffprobe -v error -show_entries stream=index,codec_type,codec_name,pix_fmt -show_entries format=duration -of json /home/seunghyeong/reelforge/tmp/gate-work/p5/l3-12-long-video/project/out/main.mp4",
          "exitCode": 0,
          "streams": [
            {
              "index": 0,
              "codec_name": "h264",
              "codec_type": "video",
              "pix_fmt": "yuv420p"
            },
            {
              "index": 1,
              "codec_name": "aac",
              "codec_type": "audio"
            }
          ],
          "stderrTail": ""
        }
      }
    },
    {
      "id": "pipeline-artifacts-complete",
      "pass": true,
      "measured": {
        "sceneSpecsScenes": 12,
        "audioMetaScenes": 12,
        "manifestScenes": 12,
        "pipelineReport": "tmp/gate-work/p5/l3-12-long-video/project/reports/pipeline-gate-report.json",
        "pipelineReportPass": true,
        "pipelineReportExitCode": 0
      }
    }
  ],
  "inputSet": [
    "research/06-plan/VERIFICATION-PLAN.md",
    "research/08-audit/RESOLUTION.md",
    "src/gates/p5-common.mjs",
    "src/gates/p5-l3-12-long-video.mjs",
    "tests/scenarios/l3-12-long-video.md"
  ],
  "canonicalInputMerkleHash": "33e0815eda148578db35e3fb1760fa40086090f295fe418c526f2661129d8d60",
  "evidenceHash": "d287bca643ab338f85ea8e47175a0e2b986c50f72723563aba75423e607f4655",
  "gateScriptHash": "233c55e0247c4be9bef806261131c75194f6f898ad88f415ce7b67062766d241",
  "gitCommit": "95a5dae30e032f13a9158b4d4dcafb19314f6f5f",
  "command": "node bin/vf gate all --profile full --execute",
  "exitCode": 0,
  "startedAt": "2026-07-08T08:03:21.902Z",
  "finishedAt": "2026-07-08T08:04:44.745Z"
}
